{
  "daily": {
    "date": "Friday, March 20",
    "roster_impact": [],
    "upcoming_starts": [],
    "streaming_opportunities": [],
    "hot_free_agents": [],
    "breakout_watch": [],
    "bench_candidates": [],
    "prospect_callouts": [],
    "farm_report": "",
    "baseball_pulse": "**Most Actionable Fantasy Intel:**\n\n**Injury Watch & Roster Moves:** Kyle Stowers (Orioles) suffered a hamstring injury during spring training\u2014monitor his status closely as we near Opening Day. Kyle Harrison (Giants) is dealing with a blister issue; timeline unclear but worth tracking. Carlos Est\u00e9vez (Royals) continues to show velocity concerns, sitting just over 90 MPH on his fastball\u20145 MPH below last season's average with a week to go. This is a red flag for a high-leverage closer in early drafts. Alek Manoah is working through a fingernail issue. Multiple depth pieces (Blake Perkins, River Ryan, Jasson Dominguez, Yerry De los Santos, Kenedy Corona, Payton Henry) have been optioned/reassigned to minor leagues, clearing roster spots.\n\n**Opening Day Starters Locked In:** Chris Sale (Braves), Tanner Bibee (Guardians), Joe Ryan (Twins), Cristopher Sanchez (Phillies), Logan Webb (Giants), and Yoshinobu Yamamoto (Dodgers) are confirmed for Opening Day. Yamamoto looked sharp early in spring action. Salvatore Perez is back and active for the Royals after returning to the lineup.\n\n**Spring Training Standouts & Stream Candidates:** Jake Bauers (Brewers) is having an exceptional spring with multiple power displays\u2014monitor if he gets consistent AB's. Salvador Perez homered in his return. Tyler Soderstrom (Athletics) is back in Cactus League action after injury. Cole Young (Mariners) has 5 spring HRs. Lawrence Butler is returning to the outfield. These are low-rostered names worth checking waiver wire depth charts.\n\n**Bottom Line:** Most actionable items are injury-related (Stowers, Est\u00e9vez, Harrison watch) and opening day pitcher confirmations. The feed is heavy on prospect highlights and spring training noise with limited roster-impact intel\u2014standard pre-season churn. Focus on monitoring Est\u00e9vez velocity and Stowers status before Week 1."
  }
}